ocm_mcp_server.py
iflow_mcp_maorfr_ocm_mcp-0.1.6.dist-info/METADATA
iflow_mcp_maorfr_ocm_mcp-0.1.6.dist-info/WHEEL
iflow_mcp_maorfr_ocm_mcp-0.1.6.dist-info/entry_points.txt
iflow_mcp_maorfr_ocm_mcp-0.1.6.dist-info/top_level.txt
iflow_mcp_maorfr_ocm_mcp-0.1.6.dist-info/RECORD
