Metadata-Version: 2.4
Name: iflow-mcp-maorfr-ocm-mcp
Version: 0.1.6
Summary: MCP server for Red Hat OpenShift Cluster Manager
Requires-Python: >=3.11
Requires-Dist: httpx==0.28.1
Requires-Dist: mcp==1.10.1
